cat_jump/main.py
cat_jump-0.1.12.dist-info/licenses/LICENSE
cat_jump-0.1.12.dist-info/METADATA
cat_jump-0.1.12.dist-info/WHEEL
cat_jump-0.1.12.dist-info/entry_points.txt
cat_jump-0.1.12.dist-info/top_level.txt
cat_jump-0.1.12.dist-info/RECORD
