Metadata-Version: 2.4
Name: cat-jump
Version: 0.1.12
Summary: A terminal-based ASCII cat jump game
Author-email: gwondoo <kdh30166568@gmail.com>
License: MIT License
Project-URL: Homepage, https://github.com/gwondoo/cat_jump
Requires-Python: >=3.7
License-File: LICENSE
Requires-Dist: wcwidth
Dynamic: license-file
